CHANGES.md
LICENSE.md
MANIFEST.in
README.md
README.rst
setup.py
magento/__init__.py
magento/magento_api.py
magento/magento_ipython_shell.py
python_magento.egg-info/PKG-INFO
python_magento.egg-info/SOURCES.txt
python_magento.egg-info/dependency_links.txt
python_magento.egg-info/entry_points.txt
python_magento.egg-info/requires.txt
python_magento.egg-info/top_level.txt