Metadata-Version: 1.1
Name: python-magento
Version: 1.0.0
Summary: A Python wrapper to the Magento XML-RPC API.
Home-page: https://github.com/bernieke/python-magento
Author: Bernard Kerckenaere
Author-email: bernieke@bernieke.com
License: MIT License
Platform: UNKNOWN
Classifier: Development Status :: 5 - Production/Stable
Classifier: Intended Audience :: Developers
Classifier: Natural Language :: English
Classifier: License :: OSI Approved :: MIT License
Classifier: Programming Language :: Python
Classifier: Programming Language :: Python :: 2.7
Classifier: Programming Language :: Python :: 3.3
Classifier: Programming Language :: Python :: 3.4
Classifier: Programming Language :: Python :: 3.5
